jsuniv_xx/__init__.py
jsuniv_xx/test.py
jsuniv_xx/xx/__init__.py
jsuniv_xx/xx/test.py
jsuniv_xx-0.1.dist-info/METADATA
jsuniv_xx-0.1.dist-info/RECORD
jsuniv_xx-0.1.dist-info/WHEEL
jsuniv_xx-0.1.dist-info/top_level.txt
