Metadata-Version: 2.1
Name: jsuniv-xx
Version: 0.1
Summary: AIAgorithmPack
Home-page: https://blog.csdn.net/qq_41375318/article/details/115568470
Author: major_s
Author-email: 1171657161@qq.com
License: UNKNOWN
Platform: UNKNOWN
